pyradamsa/version.py
pyradamsa/__init__.py
pyradamsa/pyradamsa.py
pyradamsa/lib/libradamsa.abi3.so
pyradamsa-0.1.0.dist-info/RECORD
pyradamsa-0.1.0.dist-info/LICENSE
pyradamsa-0.1.0.dist-info/METADATA
pyradamsa-0.1.0.dist-info/WHEEL
pyradamsa-0.1.0.dist-info/top_level.txt
