Metadata-Version: 2.1
Name: pyradamsa
Version: 0.1.0
Summary: Python bindings for radamsa fuzzing library.
Home-page: https://github.com/tsundokul/pyradamsa
Author: Daniel Timofte @tim17d
Author-email: timofte.daniel@tuta.io
License: MIT License
Keywords: radamsa fuzzing libradamsa
Platform: UNKNOWN
Classifier: Development Status :: 4 - Beta
Classifier: Topic :: Security
Classifier: Operating System :: POSIX :: Linux
Classifier: License :: OSI Approved :: MIT License
Classifier: Programming Language :: Python :: 3
